README.rst
setup.py
cinp/__init__.py
cinp/client.py
cinp/client_test.py
cinp/common.py
cinp/common_test.py
cinp/django_file_handler.py
cinp/orm_django.py
cinp/readers.py
cinp/server_common.py
cinp/server_common_test.py
cinp/server_werkzeug.py
cinp/server_werkzeug_test.py
cinp.egg-info/PKG-INFO
cinp.egg-info/SOURCES.txt
cinp.egg-info/dependency_links.txt
cinp.egg-info/top_level.txt