Metadata-Version: 1.1
Name: cinp
Version: 0.9.6
Summary: CInP, Concise Interaction Protocol
Home-page: https://github.com/cinp/python
Author: Peter Howe
Author-email: pnhowe@gmail.com
License: Apache2
Platform: UNKNOWN
Classifier: Development Status :: 4 - Beta
Classifier: Intended Audience :: Developers
Classifier: License :: OSI Approved :: Apache Software License
Classifier: Programming Language :: Python :: 3
Classifier: Programming Language :: Python :: 3.4
